pachamalayalam/__init__.py
pachamalayalam/transpiler.py
PachaMalayalam-0.2.0.dist-info/LICENSE
PachaMalayalam-0.2.0.dist-info/METADATA
PachaMalayalam-0.2.0.dist-info/WHEEL
PachaMalayalam-0.2.0.dist-info/entry_points.txt
PachaMalayalam-0.2.0.dist-info/top_level.txt
PachaMalayalam-0.2.0.dist-info/RECORD
