Metadata-Version: 2.1
Name: PachaMalayalam
Version: 0.2.0
Summary: A transpiler for writing Python code using Malayalam keywords
Home-page: https://github.com/bannawanadoor27/PachaMalayalam
Author: bannawandoor27
Author-email: bannawandoor@gmail.com
License: UNKNOWN
Platform: UNKNOWN
Classifier: Programming Language :: Python :: 3
Classifier: License :: OSI Approved :: MIT License
Classifier: Operating System :: OS Independent
Requires-Python: >=3.7
License-File: LICENSE
